lab4/task_1.v


module task_1(
	input clk, reset,
    output reg[15:0] q);

always @(posedge clk) begin
    if (reset) begin
            q <= 16'd0;
    end
    else begin
        q <= (q==16'd999) ? 0:q+1;
    end
end

endmodule

lab4/task_2.v


module task_2(
	input clk, shift_ena, count_ena, data,
    output reg [3:0] q);

    always @(posedge clk) begin
        if (shift_ena) begin
            q <= {q[2:0], data};
        end
        else begin
            q <= (count_ena) ? q-1:q;
        end
    end

endmodule

lab4/task_2_tb.v
`timescale 1ns/100ps // 1 ns time unit, 100 ps resolution
// `include "task_1.v"

module task_2_tb;
	
	reg clk, shift_ena, count_ena, data;

    wire[3:0] q;

	task_2 tsk0
	(
		.clk(clk),
        .shift_ena(shift_ena),
		.count_ena(count_ena),
		.data(data),
		.q(q)
	);


	initial
	begin
	$display ("###################################################");
	$display ("Start TestBench");
	clk = 0;
	shift_ena = 1;
	count_ena = 0;
	data = 0;
	end

	initial 
	begin
		$dumpfile ("wave.vcd");
		$dumpvars(0, task_2_tb);
	end

	always
		#5 clk = !clk;

	initial begin

		@ (posedge clk);
		@ (posedge clk);
		@ (posedge clk);
		@ (posedge clk);

		shift_ena <= 0;
		data <= 'x;

		@ (posedge clk);
		@ (posedge clk);

		shift_ena <= 1;
		data <= 1;

		@ (posedge clk);

		data <= 0;

		@ (posedge clk);
		@ (posedge clk);

		data <= 1;

		@ (posedge clk);

		shift_ena <= 0;
		data <= 'x;

		@ (posedge clk);
		@ (posedge clk);
		@ (posedge clk);

		count_ena <= 1;

		repeat(5) begin
			@ (posedge clk);
		end

		count_ena <= 0;

		@ (posedge clk);
		@ (posedge clk);

		$display ("###################################################");
		$finish();
	end

	initial begin
		$monitor("t=%-4d: clk = %h, shift_ena = %h, count_ena = %h, data = %h, q = %d", $time, clk, shift_ena, count_ena, data, q);
	end

endmodule

lab4/out/wave.vcd
$date
	Fri Oct 18 23:35:09 2024
$end
$version
	Icarus Verilog
$end
$timescale
	100ps
$end
$scope module task_2_tb $end
$var wire 4 ! q [3:0] $end
$var reg 1 " clk $end
$var reg 1 # count_ena $end
$var reg 1 $ data $end
$var reg 1 % shift_ena $end
$scope module tsk0 $end
$var wire 1 " clk $end
$var wire 1 # count_ena $end
$var wire 1 $ data $end
$var wire 1 % shift_ena $end
$var reg 4 & q [3:0] $end
$upscope $end
$upscope $end
$enddefinitions $end
$comment Show the parameter values. $end
$dumpall
$end
#0
$dumpvars
bx &
1%
0$
0#
0"
bx !
$end
#50
bx0 !
bx0 &
1"
#100
0"
#150
bx00 !
bx00 &
1"
#200
0"
#250
bx000 !
bx000 &
1"
#300
0"
#350
x$
0%
b0 !
b0 &
1"
#400
0"
#450
1"
#500
0"
#550
1$
1%
1"
#600
0"
#650
b1 !
b1 &
0$
1"
#700
0"
#750
b10 !
b10 &
1"
#800
0"
#850
b100 !
b100 &
1$
1"
#900
0"
#950
x$
0%
b1001 !
b1001 &
1"
#1000
0"
#1050
1"
#1100
0"
#1150
1"
#1200
0"
#1250
1#
1"
#1300
0"
#1350
b1000 !
b1000 &
1"
#1400
0"
#1450
b111 !
b111 &
1"
#1500
0"
#1550
b110 !
b110 &
1"
#1600
0"
#1650
b101 !
b101 &
1"
#1700
0"
#1750
0#
b100 !
b100 &
1"
