lab3/task_1.v


module task_1(
	input a, b, c, d,
    output q );

assign q = b & (c | d) | a & (c | d);

endmodule

lab3/task_1_tb.v
`timescale 1ns/100ps // 1 ns time unit, 100 ps resolution
// `include "task_1.v"

module task_1_tb;
	reg a=0, b=0, c=0, d=0;

    wire q;

	task_1 tsk0
	(
		.a(a),
        .b(b),
        .c(c),
        .d(d),
		.q(q)
	);

	initial begin
		$dumpfile("wave.vcd");		// create a VCD waveform dump called "wave.vcd"
		$dumpvars(0, task_1_tb);		// dump variable changes in the testbench
									// and all modules under it
		#5 a=0; b=0; c=0; d=0;
		#5;a=0; b=0; c=0; d=1;
		#5;a=0; b=0; c=1; d=0;
		#5;a=0; b=0; c=1; d=1;
		#5;a=0; b=1; c=0; d=0;
		#5;a=0; b=1; c=0; d=1;
		#5;a=0; b=1; c=1; d=0;
		#5;a=0; b=1; c=1; d=1;
		#5;a=1; b=0; c=0; d=0;
		#5;a=1; b=0; c=0; d=1;
		#5;a=1; b=0; c=1; d=0;
		#5;a=1; b=0; c=1; d=1;
		#5;a=1; b=1; c=0; d=0;
		#5;a=1; b=1; c=0; d=1;
		#5;a=1; b=1; c=1; d=0;
		#5;a=1; b=1; c=1; d=1;
		#5;a=0; b=0; c=0; d=0;
		#5;a=0; b=0; c=0; d=1;
        #5
	
		$finish();
	end

	initial begin
		$monitor("t=%-4d: a = %d, b = %d, c = %d, d = %d, q = %d", $time, a, b, c, d, q);
	end
endmodule

lab3/build/wave.vcd
$date
	Fri Oct 11 20:25:30 2024
$end
$version
	Icarus Verilog
$end
$timescale
	100ps
$end
$scope module task_1_tb $end
$var wire 1 ! q $end
$var reg 1 " a $end
$var reg 1 # b $end
$var reg 1 $ c $end
$var reg 1 % d $end
$scope module tsk0 $end
$var wire 1 " a $end
$var wire 1 # b $end
$var wire 1 $ c $end
$var wire 1 % d $end
$var wire 1 ! q $end
$upscope $end
$upscope $end
$enddefinitions $end
$comment Show the parameter values. $end
$dumpall
$end
#0
$dumpvars
0%
0$
0#
0"
z!
$end
#100
1%
#150
0%
1$
#200
1%
#250
0%
0$
1#
#300
1%
#350
0%
1$
#400
1%
#450
0%
0$
0#
1"
#500
1%
#550
0%
1$
#600
1%
#650
0%
0$
1#
#700
1%
#750
0%
1$
#800
1%
#850
0%
0$
0#
0"
#900
1%
